genpei/__init__.py
genpei/app.py
genpei/const.py
genpei/controller.py
genpei/run.py
genpei/service-info.json
genpei/type.py
genpei/util.py
genpei-1.0.1.dist-info/LICENSE
genpei-1.0.1.dist-info/METADATA
genpei-1.0.1.dist-info/WHEEL
genpei-1.0.1.dist-info/entry_points.txt
genpei-1.0.1.dist-info/top_level.txt
genpei-1.0.1.dist-info/RECORD
